{
	"packages" : [
 		{
			"product" : "FabMo-Engine",
			"os" : "linux",
			"platform" : "edison",
			"version" : "v1.2.2",
			"changelog" : " * Temporarily remove Bonjour support",
			"url" : "https://github.com/FabMo/FabMo-Engine/releases/download/v1.2.2/FabMo-Engine_linux_edison_v1-2-2.fmp"

 		},
		{
			   "os": "linux",
			   "product": "FabMo-Engine",
			   "platform": "edison",
			   "system": "handibot",
			   "updaterNeeded": "v2.0.0",
			   "version": "v1.2.5",
			   "md5": "a91f11055093fce520b3a6909da058a0",
			   "changelog" : " * Improved support for automatic updates in the configuration app",
			   "url" : "https://github.com/FabMo/FabMo-Engine/releases/download/v1.2.5/fabmo-engine-linux-edison-v1-2-5.fmp"
		},
		{
			   "os": "linux",
			   "product": "FabMo-Updater",
			   "platform": "edison",
			   "system": "handibot",
			   "updaterNeeded": "v2.0.0",
			   "version": "v2.1.8",
			   "md5": "d41d8cd98f00b204e9800998ecf8427e",
			   "changelog" : " * Fix order of name/password fields",
			   "url" : "https://github.com/FabMo/FabMo-Updater/releases/download/v2.1.8/FabMo-Updater_linux_edison_v2-1-8.fmp"
		},
		{
			   "os": "linux",
			   "product": "FabMo-Updater",
			   "platform": "edison",
			   "system": "handibot",
			   "updaterNeeded": "v2.0.0",
			   "version": "v2.1.9",
			   "changelog" : " * Fix re-locking of partition, which was not always happening",
			   "url" : "https://github.com/FabMo/FabMo-Updater/releases/download/v2.1.9/FabMo-Updater-linux-edison-v2-1-8.fmp",
			   "md5": "ecec71a676b521c812ec0b2d6bb1d41f"
		}
	]
}
